{
  "general_info": {
    "registros_region_total": 609259,
    "registros_continentales": 609259,
    "registros_marinos": 0,
    "especies_region_total": 7944,
    "especies_continentales": 7944,
    "especies_marinas": "NA",
    "subtipo": "Departamento",
    "label": "Tolima",
    "main_text": "A través del SiB Colombia se han publicado 609259 observaciones\npara el Departamento de Tolima. Estos datos hacen referencia a un total de\n7944 especies, de las cuales 7944 habitan el territorio\nal interior del continente y NA en el mar.\nTenga en cuenta que algunas especies pueden tener hábitats continentales y marinos por la cual\nla especie se incluye dentro del conteo de ambas coberturas."
  },
  "slides": [
    {
      "id": "slide1",
      "layout": "title/(text|chart)",
      "title": "TOLIMA VS COLOMBIA",
      "description": "El departamento de tolima tiene alrededor del 4% de las observaciones de especies del país.",
      "chart_type": "image",
      "chart_url": "static/charts/tolima/reg_vs_parent.png"
    },
    {
      "id": "slide2",
      "layout": "text-blocks",
      "texts": [
        "Las especies de animales con más registros son: Coragyps atratus (7153), Tyrannus melancholicus (6513), Thraupis episcopus (6476), Zonotrichia capensis (5684), Sicalis flaveola (5040).",
        "Las especies de plantas con más registros son: Ceroxylon quindiuense (4227), Manihot esculenta (920), Astronium graveolens (873), Trichilia acuminata (861), Espeletia hartwegiana (841)."
      ]
    },
    {
      "id": "slide3",
      "layout": "title/(chart|chart)",
      "title": "LOS MUNICIPIOS CON MÁS: ",
      "description": "",
      "chart_type": "html",
      "chart1_url": "static/charts/tolima/muni_mas_endemicas.html",
      "chart2_url": "static/charts/tolima/muni_mas_amenazadas.html"
    }
  ],
  "grupos_biologicos": [
    {
      "slug": "abejas",
      "slug_region": "tolima",
      "slug_grupo_biologico": "abejas",
      "especies_region_total": 32,
      "especies_amenazadas_nacional_total": 1,
      "especies_amenazadas_nacional_cr": 1,
      "especies_amenazadas_nacional_en": 0,
      "especies_amenazadas_nacional_vu": 0,
      "especies_cites_total": 0,
      "especies_cites_i": 0,
      "especies_cites_ii": 0,
      "especies_cites_i_ii": 0,
      "especies_cites_iii": 0,
      "especies_endemicas": 0,
      "especies_migratorias": 0,
      "especies_exoticas": 1,
      "especies_invasoras": 0,
      "especies_amenazadas_global_total": 1,
      "especies_amenazadas_global_ex": 0,
      "especies_amenazadas_global_ew": 0,
      "especies_amenazadas_global_cr": 0,
      "especies_amenazadas_global_en": 0,
      "especies_amenazadas_global_vu": 0,
      "especies_amenazadas_global_nt": 0,
      "especies_amenazadas_global_lc": 1,
      "especies_amenazadas_global_dd": 0,
      "registros_region_total": 387,
      "registros_amenazadas_nacional_total": 1,
      "registros_amenazadas_nacional_cr": 1,
      "registros_amenazadas_nacional_en": 0,
      "registros_amenazadas_nacional_vu": 0,
      "registros_cites_total": 0,
      "registros_cites_i": 0,
      "registros_cites_ii": 0,
      "registros_cites_i_ii": 0,
      "registros_cites_iii": 0,
      "registros_endemicas": 0,
      "registros_exoticas": 12,
      "registros_invasoras": 0,
      "registros_migratorias": 0,
      "registros_amenazadas_global_total": 1,
      "registros_amenazadas_global_ex": 0,
      "registros_amenazadas_global_ew": 0,
      "registros_amenazadas_global_cr": 0,
      "registros_amenazadas_global_en": 0,
      "registros_amenazadas_global_vu": 0,
      "registros_amenazadas_global_nt": 0,
      "registros_amenazadas_global_lc": 1,
      "registros_amenazadas_global_dd": 0
    },
    {
      "slug": "anfibios",
      "slug_region": "tolima",
      "slug_grupo_biologico": "anfibios",
      "especies_region_total": 120,
      "especies_amenazadas_nacional_total": 5,
      "especies_amenazadas_nacional_cr": 1,
      "especies_amenazadas_nacional_en": 1,
      "especies_amenazadas_nacional_vu": 3,
      "especies_cites_total": 3,
      "especies_cites_i": 0,
      "especies_cites_ii": 3,
      "especies_cites_i_ii": 0,
      "especies_cites_iii": 0,
      "especies_endemicas": 0,
      "especies_migratorias": 0,
      "especies_exoticas": 1,
      "especies_invasoras": 1,
      "especies_amenazadas_global_total": 106,
      "especies_amenazadas_global_ex": 0,
      "especies_amenazadas_global_ew": 0,
      "especies_amenazadas_global_cr": 3,
      "especies_amenazadas_global_en": 5,
      "especies_amenazadas_global_vu": 13,
      "especies_amenazadas_global_nt": 9,
      "especies_amenazadas_global_lc": 76,
      "especies_amenazadas_global_dd": 0,
      "registros_region_total": 3887,
      "registros_amenazadas_nacional_total": 127,
      "registros_amenazadas_nacional_cr": 1,
      "registros_amenazadas_nacional_en": 3,
      "registros_amenazadas_nacional_vu": 123,
      "registros_cites_total": 148,
      "registros_cites_i": 0,
      "registros_cites_ii": 148,
      "registros_cites_i_ii": 0,
      "registros_cites_iii": 0,
      "registros_endemicas": 0,
      "registros_exoticas": 1,
      "registros_invasoras": 1,
      "registros_migratorias": 0,
      "registros_amenazadas_global_total": 3144,
      "registros_amenazadas_global_ex": 0,
      "registros_amenazadas_global_ew": 0,
      "registros_amenazadas_global_cr": 52,
      "registros_amenazadas_global_en": 51,
      "registros_amenazadas_global_vu": 302,
      "registros_amenazadas_global_nt": 220,
      "registros_amenazadas_global_lc": 2519,
      "registros_amenazadas_global_dd": 0
    },
    {
      "slug": "animales",
      "slug_region": "tolima",
      "slug_grupo_biologico": "animales",
      "especies_region_total": 2884,
      "especies_amenazadas_nacional_total": 79,
      "especies_amenazadas_nacional_cr": 9,
      "especies_amenazadas_nacional_en": 17,
      "especies_amenazadas_nacional_vu": 53,
      "especies_cites_total": 198,
      "especies_cites_i": 13,
      "especies_cites_ii": 171,
      "especies_cites_i_ii": 1,
      "especies_cites_iii": 13,
      "especies_endemicas": 131,
      "especies_migratorias": 89,
      "especies_exoticas": 28,
      "especies_invasoras": 3,
      "especies_amenazadas_global_total": 1345,
      "especies_amenazadas_global_ex": 0,
      "especies_amenazadas_global_ew": 0,
      "especies_amenazadas_global_cr": 7,
      "especies_amenazadas_global_en": 15,
      "especies_amenazadas_global_vu": 55,
      "especies_amenazadas_global_nt": 50,
      "especies_amenazadas_global_lc": 1186,
      "especies_amenazadas_global_dd": 32,
      "registros_region_total": 527997,
      "registros_amenazadas_nacional_total": 6414,
      "registros_amenazadas_nacional_cr": 393,
      "registros_amenazadas_nacional_en": 907,
      "registros_amenazadas_nacional_vu": 5114,
      "registros_cites_total": 55688,
      "registros_cites_i": 1045,
      "registros_cites_ii": 52464,
      "registros_cites_i_ii": 2,
      "registros_cites_iii": 2177,
      "registros_endemicas": 12241,
      "registros_exoticas": 8867,
      "registros_invasoras": 558,
      "registros_migratorias": 30388,
      "registros_amenazadas_global_total": 406983,
      "registros_amenazadas_global_ex": 0,
      "registros_amenazadas_global_ew": 0,
      "registros_amenazadas_global_cr": 343,
      "registros_amenazadas_global_en": 152,
      "registros_amenazadas_global_vu": 4264,
      "registros_amenazadas_global_nt": 5179,
      "registros_amenazadas_global_lc": 396892,
      "registros_amenazadas_global_dd": 153
    },
    {
      "slug": "aracnidos",
      "slug_region": "tolima",
      "slug_grupo_biologico": "aracnidos",
      "especies_region_total": 77,
      "especies_amenazadas_nacional_total": 2,
      "especies_amenazadas_nacional_cr": 0,
      "especies_amenazadas_nacional_en": 1,
      "especies_amenazadas_nacional_vu": 1,
      "especies_cites_total": 0,
      "especies_cites_i": 0,
      "especies_cites_ii": 0,
      "especies_cites_i_ii": 0,
      "especies_cites_iii": 0,
      "especies_endemicas": 0,
      "especies_migratorias": 0,
      "especies_exoticas": 1,
      "especies_invasoras": 0,
      "especies_amenazadas_global_total": 1,
      "especies_amenazadas_global_ex": 0,
      "especies_amenazadas_global_ew": 0,
      "especies_amenazadas_global_cr": 0,
      "especies_amenazadas_global_en": 0,
      "especies_amenazadas_global_vu": 0,
      "especies_amenazadas_global_nt": 0,
      "especies_amenazadas_global_lc": 1,
      "especies_amenazadas_global_dd": 0,
      "registros_region_total": 1995,
      "registros_amenazadas_nacional_total": 3,
      "registros_amenazadas_nacional_cr": 0,
      "registros_amenazadas_nacional_en": 1,
      "registros_amenazadas_nacional_vu": 2,
      "registros_cites_total": 0,
      "registros_cites_i": 0,
      "registros_cites_ii": 0,
      "registros_cites_i_ii": 0,
      "registros_cites_iii": 0,
      "registros_endemicas": 0,
      "registros_exoticas": 2,
      "registros_invasoras": 0,
      "registros_migratorias": 0,
      "registros_amenazadas_global_total": 10,
      "registros_amenazadas_global_ex": 0,
      "registros_amenazadas_global_ew": 0,
      "registros_amenazadas_global_cr": 0,
      "registros_amenazadas_global_en": 0,
      "registros_amenazadas_global_vu": 0,
      "registros_amenazadas_global_nt": 0,
      "registros_amenazadas_global_lc": 10,
      "registros_amenazadas_global_dd": 0
    },
    {
      "slug": "aves",
      "slug_region": "tolima",
      "slug_grupo_biologico": "aves",
      "especies_region_total": 889,
      "especies_amenazadas_nacional_total": 41,
      "especies_amenazadas_nacional_cr": 4,
      "especies_amenazadas_nacional_en": 11,
      "especies_amenazadas_nacional_vu": 26,
      "especies_cites_total": 155,
      "especies_cites_i": 5,
      "especies_cites_ii": 145,
      "especies_cites_i_ii": 0,
      "especies_cites_iii": 5,
      "especies_endemicas": 27,
      "especies_migratorias": 89,
      "especies_exoticas": 9,
      "especies_invasoras": 0,
      "especies_amenazadas_global_total": 817,
      "especies_amenazadas_global_ex": 0,
      "especies_amenazadas_global_ew": 0,
      "especies_amenazadas_global_cr": 1,
      "especies_amenazadas_global_en": 3,
      "especies_amenazadas_global_vu": 25,
      "especies_amenazadas_global_nt": 30,
      "especies_amenazadas_global_lc": 757,
      "especies_amenazadas_global_dd": 1,
      "registros_region_total": 403406,
      "registros_amenazadas_nacional_total": 5932,
      "registros_amenazadas_nacional_cr": 384,
      "registros_amenazadas_nacional_en": 823,
      "registros_amenazadas_nacional_vu": 4725,
      "registros_cites_total": 53808,
      "registros_cites_i": 810,
      "registros_cites_ii": 51883,
      "registros_cites_i_ii": 0,
      "registros_cites_iii": 1115,
      "registros_endemicas": 5488,
      "registros_exoticas": 7593,
      "registros_invasoras": 0,
      "registros_migratorias": 30388,
      "registros_amenazadas_global_total": 387248,
      "registros_amenazadas_global_ex": 0,
      "registros_amenazadas_global_ew": 0,
      "registros_amenazadas_global_cr": 223,
      "registros_amenazadas_global_en": 13,
      "registros_amenazadas_global_vu": 3366,
      "registros_amenazadas_global_nt": 4614,
      "registros_amenazadas_global_lc": 379029,
      "registros_amenazadas_global_dd": 3
    },
    {
      "slug": "dipteros",
      "slug_region": "tolima",
      "slug_grupo_biologico": "dipteros",
      "especies_region_total": 60,
      "especies_amenazadas_nacional_total": 0,
      "especies_amenazadas_nacional_cr": 0,
      "especies_amenazadas_nacional_en": 0,
      "especies_amenazadas_nacional_vu": 0,
      "especies_cites_total": 0,
      "especies_cites_i": 0,
      "especies_cites_ii": 0,
      "especies_cites_i_ii": 0,
      "especies_cites_iii": 0,
      "especies_endemicas": 0,
      "especies_migratorias": 0,
      "especies_exoticas": 3,
      "especies_invasoras": 0,
      "especies_amenazadas_global_total": 0,
      "especies_amenazadas_global_ex": 0,
      "especies_amenazadas_global_ew": 0,
      "especies_amenazadas_global_cr": 0,
      "especies_amenazadas_global_en": 0,
      "especies_amenazadas_global_vu": 0,
      "especies_amenazadas_global_nt": 0,
      "especies_amenazadas_global_lc": 0,
      "especies_amenazadas_global_dd": 0,
      "registros_region_total": 11902,
      "registros_amenazadas_nacional_total": 0,
      "registros_amenazadas_nacional_cr": 0,
      "registros_amenazadas_nacional_en": 0,
      "registros_amenazadas_nacional_vu": 0,
      "registros_cites_total": 0,
      "registros_cites_i": 0,
      "registros_cites_ii": 0,
      "registros_cites_i_ii": 0,
      "registros_cites_iii": 0,
      "registros_endemicas": 0,
      "registros_exoticas": 19,
      "registros_invasoras": 0,
      "registros_migratorias": 0,
      "registros_amenazadas_global_total": 0,
      "registros_amenazadas_global_ex": 0,
      "registros_amenazadas_global_ew": 0,
      "registros_amenazadas_global_cr": 0,
      "registros_amenazadas_global_en": 0,
      "registros_amenazadas_global_vu": 0,
      "registros_amenazadas_global_nt": 0,
      "registros_amenazadas_global_lc": 0,
      "registros_amenazadas_global_dd": 0
    },
    {
      "slug": "escarabajos",
      "slug_region": "tolima",
      "slug_grupo_biologico": "escarabajos",
      "especies_region_total": 203,
      "especies_amenazadas_nacional_total": 1,
      "especies_amenazadas_nacional_cr": 0,
      "especies_amenazadas_nacional_en": 0,
      "especies_amenazadas_nacional_vu": 1,
      "especies_cites_total": 0,
      "especies_cites_i": 0,
      "especies_cites_ii": 0,
      "especies_cites_i_ii": 0,
      "especies_cites_iii": 0,
      "especies_endemicas": 0,
      "especies_migratorias": 0,
      "especies_exoticas": 2,
      "especies_invasoras": 0,
      "especies_amenazadas_global_total": 4,
      "especies_amenazadas_global_ex": 0,
      "especies_amenazadas_global_ew": 0,
      "especies_amenazadas_global_cr": 0,
      "especies_amenazadas_global_en": 0,
      "especies_amenazadas_global_vu": 0,
      "especies_amenazadas_global_nt": 0,
      "especies_amenazadas_global_lc": 4,
      "especies_amenazadas_global_dd": 0,
      "registros_region_total": 26687,
      "registros_amenazadas_nacional_total": 2,
      "registros_amenazadas_nacional_cr": 0,
      "registros_amenazadas_nacional_en": 0,
      "registros_amenazadas_nacional_vu": 2,
      "registros_cites_total": 0,
      "registros_cites_i": 0,
      "registros_cites_ii": 0,
      "registros_cites_i_ii": 0,
      "registros_cites_iii": 0,
      "registros_endemicas": 0,
      "registros_exoticas": 36,
      "registros_invasoras": 0,
      "registros_migratorias": 0,
      "registros_amenazadas_global_total": 28,
      "registros_amenazadas_global_ex": 0,
      "registros_amenazadas_global_ew": 0,
      "registros_amenazadas_global_cr": 0,
      "registros_amenazadas_global_en": 0,
      "registros_amenazadas_global_vu": 0,
      "registros_amenazadas_global_nt": 0,
      "registros_amenazadas_global_lc": 28,
      "registros_amenazadas_global_dd": 0
    },
    {
      "slug": "hongos",
      "slug_region": "tolima",
      "slug_grupo_biologico": "hongos",
      "especies_region_total": 188,
      "especies_amenazadas_nacional_total": 0,
      "especies_amenazadas_nacional_cr": 0,
      "especies_amenazadas_nacional_en": 0,
      "especies_amenazadas_nacional_vu": 0,
      "especies_cites_total": 0,
      "especies_cites_i": 0,
      "especies_cites_ii": 0,
      "especies_cites_i_ii": 0,
      "especies_cites_iii": 0,
      "especies_endemicas": 2,
      "especies_migratorias": 0,
      "especies_exoticas": 0,
      "especies_invasoras": 0,
      "especies_amenazadas_global_total": 0,
      "especies_amenazadas_global_ex": 0,
      "especies_amenazadas_global_ew": 0,
      "especies_amenazadas_global_cr": 0,
      "especies_amenazadas_global_en": 0,
      "especies_amenazadas_global_vu": 0,
      "especies_amenazadas_global_nt": 0,
      "especies_amenazadas_global_lc": 0,
      "especies_amenazadas_global_dd": 0,
      "registros_region_total": 695,
      "registros_amenazadas_nacional_total": 0,
      "registros_amenazadas_nacional_cr": 0,
      "registros_amenazadas_nacional_en": 0,
      "registros_amenazadas_nacional_vu": 0,
      "registros_cites_total": 0,
      "registros_cites_i": 0,
      "registros_cites_ii": 0,
      "registros_cites_i_ii": 0,
      "registros_cites_iii": 0,
      "registros_endemicas": 6,
      "registros_exoticas": 0,
      "registros_invasoras": 0,
      "registros_migratorias": 0,
      "registros_amenazadas_global_total": 0,
      "registros_amenazadas_global_ex": 0,
      "registros_amenazadas_global_ew": 0,
      "registros_amenazadas_global_cr": 0,
      "registros_amenazadas_global_en": 0,
      "registros_amenazadas_global_vu": 0,
      "registros_amenazadas_global_nt": 0,
      "registros_amenazadas_global_lc": 0,
      "registros_amenazadas_global_dd": 0
    },
    {
      "slug": "hormigas",
      "slug_region": "tolima",
      "slug_grupo_biologico": "hormigas",
      "especies_region_total": 55,
      "especies_amenazadas_nacional_total": 0,
      "especies_amenazadas_nacional_cr": 0,
      "especies_amenazadas_nacional_en": 0,
      "especies_amenazadas_nacional_vu": 0,
      "especies_cites_total": 0,
      "especies_cites_i": 0,
      "especies_cites_ii": 0,
      "especies_cites_i_ii": 0,
      "especies_cites_iii": 0,
      "especies_endemicas": 0,
      "especies_migratorias": 0,
      "especies_exoticas": 2,
      "especies_invasoras": 0,
      "especies_amenazadas_global_total": 0,
      "especies_amenazadas_global_ex": 0,
      "especies_amenazadas_global_ew": 0,
      "especies_amenazadas_global_cr": 0,
      "especies_amenazadas_global_en": 0,
      "especies_amenazadas_global_vu": 0,
      "especies_amenazadas_global_nt": 0,
      "especies_amenazadas_global_lc": 0,
      "especies_amenazadas_global_dd": 0,
      "registros_region_total": 1150,
      "registros_amenazadas_nacional_total": 0,
      "registros_amenazadas_nacional_cr": 0,
      "registros_amenazadas_nacional_en": 0,
      "registros_amenazadas_nacional_vu": 0,
      "registros_cites_total": 0,
      "registros_cites_i": 0,
      "registros_cites_ii": 0,
      "registros_cites_i_ii": 0,
      "registros_cites_iii": 0,
      "registros_endemicas": 0,
      "registros_exoticas": 2,
      "registros_invasoras": 0,
      "registros_migratorias": 0,
      "registros_amenazadas_global_total": 0,
      "registros_amenazadas_global_ex": 0,
      "registros_amenazadas_global_ew": 0,
      "registros_amenazadas_global_cr": 0,
      "registros_amenazadas_global_en": 0,
      "registros_amenazadas_global_vu": 0,
      "registros_amenazadas_global_nt": 0,
      "registros_amenazadas_global_lc": 0,
      "registros_amenazadas_global_dd": 0
    },
    {
      "slug": "insectos",
      "slug_region": "tolima",
      "slug_grupo_biologico": "insectos",
      "especies_region_total": 1188,
      "especies_amenazadas_nacional_total": 2,
      "especies_amenazadas_nacional_cr": 1,
      "especies_amenazadas_nacional_en": 0,
      "especies_amenazadas_nacional_vu": 1,
      "especies_cites_total": 0,
      "especies_cites_i": 0,
      "especies_cites_ii": 0,
      "especies_cites_i_ii": 0,
      "especies_cites_iii": 0,
      "especies_endemicas": 0,
      "especies_migratorias": 0,
      "especies_exoticas": 8,
      "especies_invasoras": 0,
      "especies_amenazadas_global_total": 25,
      "especies_amenazadas_global_ex": 0,
      "especies_amenazadas_global_ew": 0,
      "especies_amenazadas_global_cr": 0,
      "especies_amenazadas_global_en": 2,
      "especies_amenazadas_global_vu": 0,
      "especies_amenazadas_global_nt": 0,
      "especies_amenazadas_global_lc": 23,
      "especies_amenazadas_global_dd": 0,
      "registros_region_total": 91695,
      "registros_amenazadas_nacional_total": 3,
      "registros_amenazadas_nacional_cr": 1,
      "registros_amenazadas_nacional_en": 0,
      "registros_amenazadas_nacional_vu": 2,
      "registros_cites_total": 0,
      "registros_cites_i": 0,
      "registros_cites_ii": 0,
      "registros_cites_i_ii": 0,
      "registros_cites_iii": 0,
      "registros_endemicas": 0,
      "registros_exoticas": 69,
      "registros_invasoras": 0,
      "registros_migratorias": 0,
      "registros_amenazadas_global_total": 304,
      "registros_amenazadas_global_ex": 0,
      "registros_amenazadas_global_ew": 0,
      "registros_amenazadas_global_cr": 0,
      "registros_amenazadas_global_en": 8,
      "registros_amenazadas_global_vu": 0,
      "registros_amenazadas_global_nt": 0,
      "registros_amenazadas_global_lc": 296,
      "registros_amenazadas_global_dd": 0
    },
    {
      "slug": "invertebrados",
      "slug_region": "tolima",
      "slug_grupo_biologico": "invertebrados",
      "especies_region_total": 1340,
      "especies_amenazadas_nacional_total": 5,
      "especies_amenazadas_nacional_cr": 1,
      "especies_amenazadas_nacional_en": 2,
      "especies_amenazadas_nacional_vu": 2,
      "especies_cites_total": 1,
      "especies_cites_i": 0,
      "especies_cites_ii": 1,
      "especies_cites_i_ii": 0,
      "especies_cites_iii": 0,
      "especies_endemicas": 0,
      "especies_migratorias": 0,
      "especies_exoticas": 9,
      "especies_invasoras": 0,
      "especies_amenazadas_global_total": 38,
      "especies_amenazadas_global_ex": 0,
      "especies_amenazadas_global_ew": 0,
      "especies_amenazadas_global_cr": 1,
      "especies_amenazadas_global_en": 2,
      "especies_amenazadas_global_vu": 0,
      "especies_amenazadas_global_nt": 0,
      "especies_amenazadas_global_lc": 32,
      "especies_amenazadas_global_dd": 3,
      "registros_region_total": 98381,
      "registros_amenazadas_nacional_total": 8,
      "registros_amenazadas_nacional_cr": 1,
      "registros_amenazadas_nacional_en": 3,
      "registros_amenazadas_nacional_vu": 4,
      "registros_cites_total": 6,
      "registros_cites_i": 0,
      "registros_cites_ii": 6,
      "registros_cites_i_ii": 0,
      "registros_cites_iii": 0,
      "registros_endemicas": 0,
      "registros_exoticas": 71,
      "registros_invasoras": 0,
      "registros_migratorias": 0,
      "registros_amenazadas_global_total": 407,
      "registros_amenazadas_global_ex": 0,
      "registros_amenazadas_global_ew": 0,
      "registros_amenazadas_global_cr": 2,
      "registros_amenazadas_global_en": 8,
      "registros_amenazadas_global_vu": 0,
      "registros_amenazadas_global_nt": 0,
      "registros_amenazadas_global_lc": 393,
      "registros_amenazadas_global_dd": 4
    },
    {
      "slug": "mamiferos",
      "slug_region": "tolima",
      "slug_grupo_biologico": "mamiferos",
      "especies_region_total": 219,
      "especies_amenazadas_nacional_total": 8,
      "especies_amenazadas_nacional_cr": 0,
      "especies_amenazadas_nacional_en": 1,
      "especies_amenazadas_nacional_vu": 7,
      "especies_cites_total": 24,
      "especies_cites_i": 7,
      "especies_cites_ii": 12,
      "especies_cites_i_ii": 0,
      "especies_cites_iii": 5,
      "especies_endemicas": 14,
      "especies_migratorias": 0,
      "especies_exoticas": 5,
      "especies_invasoras": 0,
      "especies_amenazadas_global_total": 175,
      "especies_amenazadas_global_ex": 0,
      "especies_amenazadas_global_ew": 0,
      "especies_amenazadas_global_cr": 0,
      "especies_amenazadas_global_en": 3,
      "especies_amenazadas_global_vu": 9,
      "especies_amenazadas_global_nt": 6,
      "especies_amenazadas_global_lc": 148,
      "especies_amenazadas_global_dd": 9,
      "registros_region_total": 8784,
      "registros_amenazadas_nacional_total": 156,
      "registros_amenazadas_nacional_cr": 0,
      "registros_amenazadas_nacional_en": 71,
      "registros_amenazadas_nacional_vu": 85,
      "registros_cites_total": 1570,
      "registros_cites_i": 234,
      "registros_cites_ii": 337,
      "registros_cites_i_ii": 0,
      "registros_cites_iii": 999,
      "registros_endemicas": 179,
      "registros_exoticas": 34,
      "registros_invasoras": 0,
      "registros_migratorias": 0,
      "registros_amenazadas_global_total": 6907,
      "registros_amenazadas_global_ex": 0,
      "registros_amenazadas_global_ew": 0,
      "registros_amenazadas_global_cr": 0,
      "registros_amenazadas_global_en": 74,
      "registros_amenazadas_global_vu": 362,
      "registros_amenazadas_global_nt": 339,
      "registros_amenazadas_global_lc": 6086,
      "registros_amenazadas_global_dd": 46
    },
    {
      "slug": "mariposas",
      "slug_region": "tolima",
      "slug_grupo_biologico": "mariposas",
      "especies_region_total": 640,
      "especies_amenazadas_nacional_total": 0,
      "especies_amenazadas_nacional_cr": 0,
      "especies_amenazadas_nacional_en": 0,
      "especies_amenazadas_nacional_vu": 0,
      "especies_cites_total": 0,
      "especies_cites_i": 0,
      "especies_cites_ii": 0,
      "especies_cites_i_ii": 0,
      "especies_cites_iii": 0,
      "especies_endemicas": 0,
      "especies_migratorias": 0,
      "especies_exoticas": 0,
      "especies_invasoras": 0,
      "especies_amenazadas_global_total": 11,
      "especies_amenazadas_global_ex": 0,
      "especies_amenazadas_global_ew": 0,
      "especies_amenazadas_global_cr": 0,
      "especies_amenazadas_global_en": 0,
      "especies_amenazadas_global_vu": 0,
      "especies_amenazadas_global_nt": 0,
      "especies_amenazadas_global_lc": 11,
      "especies_amenazadas_global_dd": 0,
      "registros_region_total": 13684,
      "registros_amenazadas_nacional_total": 0,
      "registros_amenazadas_nacional_cr": 0,
      "registros_amenazadas_nacional_en": 0,
      "registros_amenazadas_nacional_vu": 0,
      "registros_cites_total": 0,
      "registros_cites_i": 0,
      "registros_cites_ii": 0,
      "registros_cites_i_ii": 0,
      "registros_cites_iii": 0,
      "registros_endemicas": 0,
      "registros_exoticas": 0,
      "registros_invasoras": 0,
      "registros_migratorias": 0,
      "registros_amenazadas_global_total": 246,
      "registros_amenazadas_global_ex": 0,
      "registros_amenazadas_global_ew": 0,
      "registros_amenazadas_global_cr": 0,
      "registros_amenazadas_global_en": 0,
      "registros_amenazadas_global_vu": 0,
      "registros_amenazadas_global_nt": 0,
      "registros_amenazadas_global_lc": 246,
      "registros_amenazadas_global_dd": 0
    },
    {
      "slug": "moluscos",
      "slug_region": "tolima",
      "slug_grupo_biologico": "moluscos",
      "especies_region_total": 37,
      "especies_amenazadas_nacional_total": 0,
      "especies_amenazadas_nacional_cr": 0,
      "especies_amenazadas_nacional_en": 0,
      "especies_amenazadas_nacional_vu": 0,
      "especies_cites_total": 0,
      "especies_cites_i": 0,
      "especies_cites_ii": 0,
      "especies_cites_i_ii": 0,
      "especies_cites_iii": 0,
      "especies_endemicas": 0,
      "especies_migratorias": 0,
      "especies_exoticas": 0,
      "especies_invasoras": 0,
      "especies_amenazadas_global_total": 1,
      "especies_amenazadas_global_ex": 0,
      "especies_amenazadas_global_ew": 0,
      "especies_amenazadas_global_cr": 1,
      "especies_amenazadas_global_en": 0,
      "especies_amenazadas_global_vu": 0,
      "especies_amenazadas_global_nt": 0,
      "especies_amenazadas_global_lc": 0,
      "especies_amenazadas_global_dd": 0,
      "registros_region_total": 926,
      "registros_amenazadas_nacional_total": 0,
      "registros_amenazadas_nacional_cr": 0,
      "registros_amenazadas_nacional_en": 0,
      "registros_amenazadas_nacional_vu": 0,
      "registros_cites_total": 0,
      "registros_cites_i": 0,
      "registros_cites_ii": 0,
      "registros_cites_i_ii": 0,
      "registros_cites_iii": 0,
      "registros_endemicas": 0,
      "registros_exoticas": 0,
      "registros_invasoras": 0,
      "registros_migratorias": 0,
      "registros_amenazadas_global_total": 2,
      "registros_amenazadas_global_ex": 0,
      "registros_amenazadas_global_ew": 0,
      "registros_amenazadas_global_cr": 2,
      "registros_amenazadas_global_en": 0,
      "registros_amenazadas_global_vu": 0,
      "registros_amenazadas_global_nt": 0,
      "registros_amenazadas_global_lc": 0,
      "registros_amenazadas_global_dd": 0
    },
    {
      "slug": "peces",
      "slug_region": "tolima",
      "slug_grupo_biologico": "peces",
      "especies_region_total": 178,
      "especies_amenazadas_nacional_total": 16,
      "especies_amenazadas_nacional_cr": 1,
      "especies_amenazadas_nacional_en": 1,
      "especies_amenazadas_nacional_vu": 14,
      "especies_cites_total": 3,
      "especies_cites_i": 0,
      "especies_cites_ii": 1,
      "especies_cites_i_ii": 0,
      "especies_cites_iii": 2,
      "especies_endemicas": 90,
      "especies_migratorias": 0,
      "especies_exoticas": 4,
      "especies_invasoras": 2,
      "especies_amenazadas_global_total": 107,
      "especies_amenazadas_global_ex": 0,
      "especies_amenazadas_global_ew": 0,
      "especies_amenazadas_global_cr": 1,
      "especies_amenazadas_global_en": 2,
      "especies_amenazadas_global_vu": 6,
      "especies_amenazadas_global_nt": 4,
      "especies_amenazadas_global_lc": 81,
      "especies_amenazadas_global_dd": 13,
      "registros_region_total": 11601,
      "registros_amenazadas_nacional_total": 180,
      "registros_amenazadas_nacional_cr": 2,
      "registros_amenazadas_nacional_en": 5,
      "registros_amenazadas_nacional_vu": 173,
      "registros_cites_total": 13,
      "registros_cites_i": 0,
      "registros_cites_ii": 1,
      "registros_cites_i_ii": 0,
      "registros_cites_iii": 12,
      "registros_endemicas": 6574,
      "registros_exoticas": 1168,
      "registros_invasoras": 557,
      "registros_migratorias": 0,
      "registros_amenazadas_global_total": 8096,
      "registros_amenazadas_global_ex": 0,
      "registros_amenazadas_global_ew": 0,
      "registros_amenazadas_global_cr": 62,
      "registros_amenazadas_global_en": 6,
      "registros_amenazadas_global_vu": 231,
      "registros_amenazadas_global_nt": 5,
      "registros_amenazadas_global_lc": 7735,
      "registros_amenazadas_global_dd": 57
    },
    {
      "slug": "plantas",
      "slug_region": "tolima",
      "slug_grupo_biologico": "plantas",
      "especies_region_total": 4618,
      "especies_amenazadas_nacional_total": 47,
      "especies_amenazadas_nacional_cr": 10,
      "especies_amenazadas_nacional_en": 14,
      "especies_amenazadas_nacional_vu": 23,
      "especies_cites_total": 119,
      "especies_cites_i": 2,
      "especies_cites_ii": 117,
      "especies_cites_i_ii": 0,
      "especies_cites_iii": 0,
      "especies_endemicas": 471,
      "especies_migratorias": 0,
      "especies_exoticas": 123,
      "especies_invasoras": 3,
      "especies_amenazadas_global_total": 887,
      "especies_amenazadas_global_ex": 1,
      "especies_amenazadas_global_ew": 2,
      "especies_amenazadas_global_cr": 5,
      "especies_amenazadas_global_en": 29,
      "especies_amenazadas_global_vu": 34,
      "especies_amenazadas_global_nt": 7,
      "especies_amenazadas_global_lc": 797,
      "especies_amenazadas_global_dd": 7,
      "registros_region_total": 55810,
      "registros_amenazadas_nacional_total": 4677,
      "registros_amenazadas_nacional_cr": 41,
      "registros_amenazadas_nacional_en": 4522,
      "registros_amenazadas_nacional_vu": 114,
      "registros_cites_total": 451,
      "registros_cites_i": 5,
      "registros_cites_ii": 446,
      "registros_cites_i_ii": 0,
      "registros_cites_iii": 0,
      "registros_endemicas": 3896,
      "registros_exoticas": 871,
      "registros_invasoras": 10,
      "registros_migratorias": 0,
      "registros_amenazadas_global_total": 18008,
      "registros_amenazadas_global_ex": 5,
      "registros_amenazadas_global_ew": 10,
      "registros_amenazadas_global_cr": 14,
      "registros_amenazadas_global_en": 431,
      "registros_amenazadas_global_vu": 5513,
      "registros_amenazadas_global_nt": 31,
      "registros_amenazadas_global_lc": 11927,
      "registros_amenazadas_global_dd": 31
    },
    {
      "slug": "reptiles",
      "slug_region": "tolima",
      "slug_grupo_biologico": "reptiles",
      "especies_region_total": 138,
      "especies_amenazadas_nacional_total": 4,
      "especies_amenazadas_nacional_cr": 2,
      "especies_amenazadas_nacional_en": 1,
      "especies_amenazadas_nacional_vu": 1,
      "especies_cites_total": 12,
      "especies_cites_i": 1,
      "especies_cites_ii": 9,
      "especies_cites_i_ii": 1,
      "especies_cites_iii": 1,
      "especies_endemicas": 0,
      "especies_migratorias": 0,
      "especies_exoticas": 0,
      "especies_invasoras": 0,
      "especies_amenazadas_global_total": 102,
      "especies_amenazadas_global_ex": 0,
      "especies_amenazadas_global_ew": 0,
      "especies_amenazadas_global_cr": 1,
      "especies_amenazadas_global_en": 0,
      "especies_amenazadas_global_vu": 2,
      "especies_amenazadas_global_nt": 1,
      "especies_amenazadas_global_lc": 92,
      "especies_amenazadas_global_dd": 6,
      "registros_region_total": 1860,
      "registros_amenazadas_nacional_total": 11,
      "registros_amenazadas_nacional_cr": 5,
      "registros_amenazadas_nacional_en": 2,
      "registros_amenazadas_nacional_vu": 4,
      "registros_cites_total": 143,
      "registros_cites_i": 1,
      "registros_cites_ii": 89,
      "registros_cites_i_ii": 2,
      "registros_cites_iii": 51,
      "registros_endemicas": 0,
      "registros_exoticas": 0,
      "registros_invasoras": 0,
      "registros_migratorias": 0,
      "registros_amenazadas_global_total": 1181,
      "registros_amenazadas_global_ex": 0,
      "registros_amenazadas_global_ew": 0,
      "registros_amenazadas_global_cr": 4,
      "registros_amenazadas_global_en": 0,
      "registros_amenazadas_global_vu": 3,
      "registros_amenazadas_global_nt": 1,
      "registros_amenazadas_global_lc": 1130,
      "registros_amenazadas_global_dd": 43
    },
    {
      "slug": "vertebrados",
      "slug_region": "tolima",
      "slug_grupo_biologico": "vertebrados",
      "especies_region_total": 1544,
      "especies_amenazadas_nacional_total": 74,
      "especies_amenazadas_nacional_cr": 8,
      "especies_amenazadas_nacional_en": 15,
      "especies_amenazadas_nacional_vu": 51,
      "especies_cites_total": 197,
      "especies_cites_i": 13,
      "especies_cites_ii": 170,
      "especies_cites_i_ii": 1,
      "especies_cites_iii": 13,
      "especies_endemicas": 131,
      "especies_migratorias": 89,
      "especies_exoticas": 19,
      "especies_invasoras": 3,
      "especies_amenazadas_global_total": 1307,
      "especies_amenazadas_global_ex": 0,
      "especies_amenazadas_global_ew": 0,
      "especies_amenazadas_global_cr": 6,
      "especies_amenazadas_global_en": 13,
      "especies_amenazadas_global_vu": 55,
      "especies_amenazadas_global_nt": 50,
      "especies_amenazadas_global_lc": 1154,
      "especies_amenazadas_global_dd": 29,
      "registros_region_total": 429552,
      "registros_amenazadas_nacional_total": 6406,
      "registros_amenazadas_nacional_cr": 392,
      "registros_amenazadas_nacional_en": 904,
      "registros_amenazadas_nacional_vu": 5110,
      "registros_cites_total": 55682,
      "registros_cites_i": 1045,
      "registros_cites_ii": 52458,
      "registros_cites_i_ii": 2,
      "registros_cites_iii": 2177,
      "registros_endemicas": 12241,
      "registros_exoticas": 8796,
      "registros_invasoras": 558,
      "registros_migratorias": 30388,
      "registros_amenazadas_global_total": 406576,
      "registros_amenazadas_global_ex": 0,
      "registros_amenazadas_global_ew": 0,
      "registros_amenazadas_global_cr": 341,
      "registros_amenazadas_global_en": 144,
      "registros_amenazadas_global_vu": 4264,
      "registros_amenazadas_global_nt": 5179,
      "registros_amenazadas_global_lc": 396499,
      "registros_amenazadas_global_dd": 149
    }
  ],
  "grupos_interes": [
    {
      "slug": "algas",
      "slug_region": "tolima",
      "slug_grupo_interes_conservacion": "algas",
      "especies_region_total": 4,
      "especies_amenazadas_nacional_total": 0,
      "especies_cites_total": 0,
      "especies_endemicas": 0,
      "especies_exoticas": 0,
      "especies_amenazadas_global_total": 0,
      "registros_region_total": 1236,
      "registros_amenazadas_nacional_total": 0,
      "registros_cites_total": 0,
      "registros_endemicas": 0,
      "registros_exoticas": 0,
      "registros_amenazadas_global_total": 0
    },
    {
      "slug": "bromelias-labiadas-pasifloras",
      "slug_region": "tolima",
      "slug_grupo_interes_conservacion": "bromelias-labiadas-pasifloras",
      "especies_region_total": 160,
      "especies_amenazadas_nacional_total": 10,
      "especies_amenazadas_nacional_cr": 6,
      "especies_amenazadas_nacional_en": 1,
      "especies_amenazadas_nacional_vu": 3,
      "especies_cites_total": 0,
      "especies_cites_i": 0,
      "especies_cites_ii": 0,
      "especies_cites_i_ii": 0,
      "especies_cites_iii": 0,
      "especies_endemicas": 28,
      "especies_migratorias": 0,
      "especies_exoticas": 1,
      "especies_invasoras": 0,
      "especies_amenazadas_global_total": 25,
      "especies_amenazadas_global_ex": 0,
      "especies_amenazadas_global_ew": 0,
      "especies_amenazadas_global_cr": 1,
      "especies_amenazadas_global_en": 1,
      "especies_amenazadas_global_vu": 2,
      "especies_amenazadas_global_nt": 0,
      "especies_amenazadas_global_lc": 21,
      "especies_amenazadas_global_dd": 0,
      "registros_region_total": 1047,
      "registros_amenazadas_nacional_total": 70,
      "registros_amenazadas_nacional_cr": 21,
      "registros_amenazadas_nacional_en": 2,
      "registros_amenazadas_nacional_vu": 47,
      "registros_cites_total": 0,
      "registros_cites_i": 0,
      "registros_cites_ii": 0,
      "registros_cites_i_ii": 0,
      "registros_cites_iii": 0,
      "registros_endemicas": 178,
      "registros_exoticas": 4,
      "registros_invasoras": 0,
      "registros_migratorias": 0,
      "registros_amenazadas_global_total": 98,
      "registros_amenazadas_global_ex": 0,
      "registros_amenazadas_global_ew": 0,
      "registros_amenazadas_global_cr": 2,
      "registros_amenazadas_global_en": 2,
      "registros_amenazadas_global_vu": 5,
      "registros_amenazadas_global_nt": 0,
      "registros_amenazadas_global_lc": 89,
      "registros_amenazadas_global_dd": 0
    },
    {
      "slug": "especies-maderables",
      "slug_region": "tolima",
      "slug_grupo_interes_conservacion": "especies-maderables",
      "especies_region_total": 7,
      "especies_amenazadas_nacional_total": 7,
      "especies_amenazadas_nacional_cr": 2,
      "especies_amenazadas_nacional_en": 3,
      "especies_amenazadas_nacional_vu": 2,
      "especies_cites_total": 1,
      "especies_cites_i": 0,
      "especies_cites_ii": 1,
      "especies_cites_i_ii": 0,
      "especies_cites_iii": 0,
      "especies_endemicas": 0,
      "especies_migratorias": 0,
      "especies_exoticas": 0,
      "especies_invasoras": 0,
      "especies_amenazadas_global_total": 7,
      "especies_amenazadas_global_ex": 0,
      "especies_amenazadas_global_ew": 0,
      "especies_amenazadas_global_cr": 0,
      "especies_amenazadas_global_en": 3,
      "especies_amenazadas_global_vu": 1,
      "especies_amenazadas_global_nt": 0,
      "especies_amenazadas_global_lc": 2,
      "especies_amenazadas_global_dd": 0,
      "registros_region_total": 282,
      "registros_amenazadas_nacional_total": 282,
      "registros_amenazadas_nacional_cr": 7,
      "registros_amenazadas_nacional_en": 242,
      "registros_amenazadas_nacional_vu": 33,
      "registros_cites_total": 2,
      "registros_cites_i": 0,
      "registros_cites_ii": 2,
      "registros_cites_i_ii": 0,
      "registros_cites_iii": 0,
      "registros_endemicas": 0,
      "registros_exoticas": 0,
      "registros_invasoras": 0,
      "registros_migratorias": 0,
      "registros_amenazadas_global_total": 282,
      "registros_amenazadas_global_ex": 0,
      "registros_amenazadas_global_ew": 0,
      "registros_amenazadas_global_cr": 0,
      "registros_amenazadas_global_en": 242,
      "registros_amenazadas_global_vu": 2,
      "registros_amenazadas_global_nt": 0,
      "registros_amenazadas_global_lc": 33,
      "registros_amenazadas_global_dd": 0
    },
    {
      "slug": "fanerogamas",
      "slug_region": "tolima",
      "slug_grupo_interes_conservacion": "fanerogamas",
      "especies_region_total": 20,
      "especies_amenazadas_nacional_total": 7,
      "especies_amenazadas_nacional_cr": 2,
      "especies_amenazadas_nacional_en": 1,
      "especies_amenazadas_nacional_vu": 4,
      "especies_cites_total": 0,
      "especies_cites_i": 0,
      "especies_cites_ii": 0,
      "especies_cites_i_ii": 0,
      "especies_cites_iii": 0,
      "especies_endemicas": 3,
      "especies_migratorias": 0,
      "especies_exoticas": 0,
      "especies_invasoras": 0,
      "especies_amenazadas_global_total": 12,
      "especies_amenazadas_global_ex": 0,
      "especies_amenazadas_global_ew": 0,
      "especies_amenazadas_global_cr": 0,
      "especies_amenazadas_global_en": 1,
      "especies_amenazadas_global_vu": 3,
      "especies_amenazadas_global_nt": 0,
      "especies_amenazadas_global_lc": 7,
      "especies_amenazadas_global_dd": 0,
      "registros_region_total": 350,
      "registros_amenazadas_nacional_total": 20,
      "registros_amenazadas_nacional_cr": 6,
      "registros_amenazadas_nacional_en": 1,
      "registros_amenazadas_nacional_vu": 13,
      "registros_cites_total": 0,
      "registros_cites_i": 0,
      "registros_cites_ii": 0,
      "registros_cites_i_ii": 0,
      "registros_cites_iii": 0,
      "registros_endemicas": 9,
      "registros_exoticas": 0,
      "registros_invasoras": 0,
      "registros_migratorias": 0,
      "registros_amenazadas_global_total": 266,
      "registros_amenazadas_global_ex": 0,
      "registros_amenazadas_global_ew": 0,
      "registros_amenazadas_global_cr": 0,
      "registros_amenazadas_global_en": 1,
      "registros_amenazadas_global_vu": 13,
      "registros_amenazadas_global_nt": 0,
      "registros_amenazadas_global_lc": 247,
      "registros_amenazadas_global_dd": 0
    },
    {
      "slug": "frailejones",
      "slug_region": "tolima",
      "slug_grupo_interes_conservacion": "frailejones",
      "especies_region_total": 1,
      "especies_amenazadas_nacional_total": 0,
      "especies_amenazadas_nacional_cr": 0,
      "especies_amenazadas_nacional_en": 0,
      "especies_amenazadas_nacional_vu": 0,
      "especies_cites_total": 0,
      "especies_cites_i": 0,
      "especies_cites_ii": 0,
      "especies_cites_i_ii": 0,
      "especies_cites_iii": 0,
      "especies_endemicas": 1,
      "especies_migratorias": 0,
      "especies_exoticas": 0,
      "especies_invasoras": 0,
      "especies_amenazadas_global_total": 1,
      "especies_amenazadas_global_ex": 0,
      "especies_amenazadas_global_ew": 0,
      "especies_amenazadas_global_cr": 0,
      "especies_amenazadas_global_en": 0,
      "especies_amenazadas_global_vu": 0,
      "especies_amenazadas_global_nt": 0,
      "especies_amenazadas_global_lc": 1,
      "especies_amenazadas_global_dd": 0,
      "registros_region_total": 859,
      "registros_amenazadas_nacional_total": 0,
      "registros_amenazadas_nacional_cr": 0,
      "registros_amenazadas_nacional_en": 0,
      "registros_amenazadas_nacional_vu": 0,
      "registros_cites_total": 0,
      "registros_cites_i": 0,
      "registros_cites_ii": 0,
      "registros_cites_i_ii": 0,
      "registros_cites_iii": 0,
      "registros_endemicas": 841,
      "registros_exoticas": 0,
      "registros_invasoras": 0,
      "registros_migratorias": 0,
      "registros_amenazadas_global_total": 841,
      "registros_amenazadas_global_ex": 0,
      "registros_amenazadas_global_ew": 0,
      "registros_amenazadas_global_cr": 0,
      "registros_amenazadas_global_en": 0,
      "registros_amenazadas_global_vu": 0,
      "registros_amenazadas_global_nt": 0,
      "registros_amenazadas_global_lc": 841,
      "registros_amenazadas_global_dd": 0
    },
    {
      "slug": "liquenes",
      "slug_region": "tolima",
      "slug_grupo_interes_conservacion": "liquenes",
      "especies_region_total": 138,
      "especies_amenazadas_nacional_total": 0,
      "especies_amenazadas_nacional_cr": 0,
      "especies_amenazadas_nacional_en": 0,
      "especies_amenazadas_nacional_vu": 0,
      "especies_cites_total": 0,
      "especies_cites_i": 0,
      "especies_cites_ii": 0,
      "especies_cites_i_ii": 0,
      "especies_cites_iii": 0,
      "especies_endemicas": 2,
      "especies_migratorias": 0,
      "especies_exoticas": 0,
      "especies_invasoras": 0,
      "especies_amenazadas_global_total": 0,
      "especies_amenazadas_global_ex": 0,
      "especies_amenazadas_global_ew": 0,
      "especies_amenazadas_global_cr": 0,
      "especies_amenazadas_global_en": 0,
      "especies_amenazadas_global_vu": 0,
      "especies_amenazadas_global_nt": 0,
      "especies_amenazadas_global_lc": 0,
      "especies_amenazadas_global_dd": 0,
      "registros_region_total": 502,
      "registros_amenazadas_nacional_total": 0,
      "registros_amenazadas_nacional_cr": 0,
      "registros_amenazadas_nacional_en": 0,
      "registros_amenazadas_nacional_vu": 0,
      "registros_cites_total": 0,
      "registros_cites_i": 0,
      "registros_cites_ii": 0,
      "registros_cites_i_ii": 0,
      "registros_cites_iii": 0,
      "registros_endemicas": 6,
      "registros_exoticas": 0,
      "registros_invasoras": 0,
      "registros_migratorias": 0,
      "registros_amenazadas_global_total": 0,
      "registros_amenazadas_global_ex": 0,
      "registros_amenazadas_global_ew": 0,
      "registros_amenazadas_global_cr": 0,
      "registros_amenazadas_global_en": 0,
      "registros_amenazadas_global_vu": 0,
      "registros_amenazadas_global_nt": 0,
      "registros_amenazadas_global_lc": 0,
      "registros_amenazadas_global_dd": 0
    },
    {
      "slug": "magnolias-afines",
      "slug_region": "tolima",
      "slug_grupo_interes_conservacion": "magnolias-afines",
      "especies_region_total": 7,
      "especies_amenazadas_nacional_total": 3,
      "especies_amenazadas_nacional_cr": 0,
      "especies_amenazadas_nacional_en": 1,
      "especies_amenazadas_nacional_vu": 2,
      "especies_cites_total": 0,
      "especies_cites_i": 0,
      "especies_cites_ii": 0,
      "especies_cites_i_ii": 0,
      "especies_cites_iii": 0,
      "especies_endemicas": 1,
      "especies_migratorias": 0,
      "especies_exoticas": 0,
      "especies_invasoras": 0,
      "especies_amenazadas_global_total": 5,
      "especies_amenazadas_global_ex": 0,
      "especies_amenazadas_global_ew": 0,
      "especies_amenazadas_global_cr": 0,
      "especies_amenazadas_global_en": 1,
      "especies_amenazadas_global_vu": 2,
      "especies_amenazadas_global_nt": 0,
      "especies_amenazadas_global_lc": 2,
      "especies_amenazadas_global_dd": 0,
      "registros_region_total": 33,
      "registros_amenazadas_nacional_total": 12,
      "registros_amenazadas_nacional_cr": 0,
      "registros_amenazadas_nacional_en": 1,
      "registros_amenazadas_nacional_vu": 11,
      "registros_cites_total": 0,
      "registros_cites_i": 0,
      "registros_cites_ii": 0,
      "registros_cites_i_ii": 0,
      "registros_cites_iii": 0,
      "registros_endemicas": 1,
      "registros_exoticas": 0,
      "registros_invasoras": 0,
      "registros_migratorias": 0,
      "registros_amenazadas_global_total": 25,
      "registros_amenazadas_global_ex": 0,
      "registros_amenazadas_global_ew": 0,
      "registros_amenazadas_global_cr": 0,
      "registros_amenazadas_global_en": 1,
      "registros_amenazadas_global_vu": 4,
      "registros_amenazadas_global_nt": 0,
      "registros_amenazadas_global_lc": 20,
      "registros_amenazadas_global_dd": 0
    },
    {
      "slug": "orquideas",
      "slug_region": "tolima",
      "slug_grupo_interes_conservacion": "orquideas",
      "especies_region_total": 193,
      "especies_amenazadas_nacional_total": 8,
      "especies_amenazadas_nacional_cr": 0,
      "especies_amenazadas_nacional_en": 3,
      "especies_amenazadas_nacional_vu": 5,
      "especies_cites_total": 94,
      "especies_cites_i": 2,
      "especies_cites_ii": 92,
      "especies_cites_i_ii": 0,
      "especies_cites_iii": 0,
      "especies_endemicas": 35,
      "especies_migratorias": 0,
      "especies_exoticas": 2,
      "especies_invasoras": 0,
      "especies_amenazadas_global_total": 6,
      "especies_amenazadas_global_ex": 0,
      "especies_amenazadas_global_ew": 0,
      "especies_amenazadas_global_cr": 0,
      "especies_amenazadas_global_en": 0,
      "especies_amenazadas_global_vu": 0,
      "especies_amenazadas_global_nt": 0,
      "especies_amenazadas_global_lc": 6,
      "especies_amenazadas_global_dd": 0,
      "registros_region_total": 780,
      "registros_amenazadas_nacional_total": 12,
      "registros_amenazadas_nacional_cr": 0,
      "registros_amenazadas_nacional_en": 7,
      "registros_amenazadas_nacional_vu": 5,
      "registros_cites_total": 212,
      "registros_cites_i": 5,
      "registros_cites_ii": 207,
      "registros_cites_i_ii": 0,
      "registros_cites_iii": 0,
      "registros_endemicas": 87,
      "registros_exoticas": 7,
      "registros_invasoras": 0,
      "registros_migratorias": 0,
      "registros_amenazadas_global_total": 15,
      "registros_amenazadas_global_ex": 0,
      "registros_amenazadas_global_ew": 0,
      "registros_amenazadas_global_cr": 0,
      "registros_amenazadas_global_en": 0,
      "registros_amenazadas_global_vu": 0,
      "registros_amenazadas_global_nt": 0,
      "registros_amenazadas_global_lc": 15,
      "registros_amenazadas_global_dd": 0
    },
    {
      "slug": "palmas",
      "slug_region": "tolima",
      "slug_grupo_interes_conservacion": "palmas",
      "especies_region_total": 26,
      "especies_amenazadas_nacional_total": 3,
      "especies_amenazadas_nacional_cr": 0,
      "especies_amenazadas_nacional_en": 3,
      "especies_amenazadas_nacional_vu": 0,
      "especies_cites_total": 0,
      "especies_cites_i": 0,
      "especies_cites_ii": 0,
      "especies_cites_i_ii": 0,
      "especies_cites_iii": 0,
      "especies_endemicas": 2,
      "especies_migratorias": 0,
      "especies_exoticas": 0,
      "especies_invasoras": 0,
      "especies_amenazadas_global_total": 3,
      "especies_amenazadas_global_ex": 0,
      "especies_amenazadas_global_ew": 0,
      "especies_amenazadas_global_cr": 0,
      "especies_amenazadas_global_en": 0,
      "especies_amenazadas_global_vu": 2,
      "especies_amenazadas_global_nt": 0,
      "especies_amenazadas_global_lc": 1,
      "especies_amenazadas_global_dd": 0,
      "registros_region_total": 4481,
      "registros_amenazadas_nacional_total": 4237,
      "registros_amenazadas_nacional_cr": 0,
      "registros_amenazadas_nacional_en": 4237,
      "registros_amenazadas_nacional_vu": 0,
      "registros_cites_total": 0,
      "registros_cites_i": 0,
      "registros_cites_ii": 0,
      "registros_cites_i_ii": 0,
      "registros_cites_iii": 0,
      "registros_endemicas": 8,
      "registros_exoticas": 0,
      "registros_invasoras": 0,
      "registros_migratorias": 0,
      "registros_amenazadas_global_total": 4236,
      "registros_amenazadas_global_ex": 0,
      "registros_amenazadas_global_ew": 0,
      "registros_amenazadas_global_cr": 0,
      "registros_amenazadas_global_en": 0,
      "registros_amenazadas_global_vu": 4230,
      "registros_amenazadas_global_nt": 0,
      "registros_amenazadas_global_lc": 6,
      "registros_amenazadas_global_dd": 0
    },
    {
      "slug": "pinos-afines",
      "slug_region": "tolima",
      "slug_grupo_interes_conservacion": "pinos-afines",
      "especies_region_total": 2,
      "especies_amenazadas_nacional_total": 0,
      "especies_amenazadas_nacional_cr": 0,
      "especies_amenazadas_nacional_en": 0,
      "especies_amenazadas_nacional_vu": 0,
      "especies_cites_total": 0,
      "especies_cites_i": 0,
      "especies_cites_ii": 0,
      "especies_cites_i_ii": 0,
      "especies_cites_iii": 0,
      "especies_endemicas": 0,
      "especies_migratorias": 0,
      "especies_exoticas": 1,
      "especies_invasoras": 0,
      "especies_amenazadas_global_total": 0,
      "especies_amenazadas_global_ex": 0,
      "especies_amenazadas_global_ew": 0,
      "especies_amenazadas_global_cr": 0,
      "especies_amenazadas_global_en": 0,
      "especies_amenazadas_global_vu": 0,
      "especies_amenazadas_global_nt": 0,
      "especies_amenazadas_global_lc": 0,
      "especies_amenazadas_global_dd": 0,
      "registros_region_total": 3,
      "registros_amenazadas_nacional_total": 0,
      "registros_amenazadas_nacional_cr": 0,
      "registros_amenazadas_nacional_en": 0,
      "registros_amenazadas_nacional_vu": 0,
      "registros_cites_total": 0,
      "registros_cites_i": 0,
      "registros_cites_ii": 0,
      "registros_cites_i_ii": 0,
      "registros_cites_iii": 0,
      "registros_endemicas": 0,
      "registros_exoticas": 2,
      "registros_invasoras": 0,
      "registros_migratorias": 0,
      "registros_amenazadas_global_total": 0,
      "registros_amenazadas_global_ex": 0,
      "registros_amenazadas_global_ew": 0,
      "registros_amenazadas_global_cr": 0,
      "registros_amenazadas_global_en": 0,
      "registros_amenazadas_global_vu": 0,
      "registros_amenazadas_global_nt": 0,
      "registros_amenazadas_global_lc": 0,
      "registros_amenazadas_global_dd": 0
    },
    {
      "slug": "zamias",
      "slug_region": "tolima",
      "slug_grupo_interes_conservacion": "zamias",
      "especies_region_total": 2,
      "especies_amenazadas_nacional_total": 1,
      "especies_amenazadas_nacional_cr": 1,
      "especies_amenazadas_nacional_en": 0,
      "especies_amenazadas_nacional_vu": 0,
      "especies_cites_total": 2,
      "especies_cites_i": 0,
      "especies_cites_ii": 2,
      "especies_cites_i_ii": 0,
      "especies_cites_iii": 0,
      "especies_endemicas": 1,
      "especies_migratorias": 0,
      "especies_exoticas": 0,
      "especies_invasoras": 0,
      "especies_amenazadas_global_total": 1,
      "especies_amenazadas_global_ex": 0,
      "especies_amenazadas_global_ew": 0,
      "especies_amenazadas_global_cr": 0,
      "especies_amenazadas_global_en": 0,
      "especies_amenazadas_global_vu": 0,
      "especies_amenazadas_global_nt": 1,
      "especies_amenazadas_global_lc": 0,
      "especies_amenazadas_global_dd": 0,
      "registros_region_total": 13,
      "registros_amenazadas_nacional_total": 12,
      "registros_amenazadas_nacional_cr": 12,
      "registros_amenazadas_nacional_en": 0,
      "registros_amenazadas_nacional_vu": 0,
      "registros_cites_total": 13,
      "registros_cites_i": 0,
      "registros_cites_ii": 13,
      "registros_cites_i_ii": 0,
      "registros_cites_iii": 0,
      "registros_endemicas": 12,
      "registros_exoticas": 0,
      "registros_invasoras": 0,
      "registros_migratorias": 0,
      "registros_amenazadas_global_total": 1,
      "registros_amenazadas_global_ex": 0,
      "registros_amenazadas_global_ew": 0,
      "registros_amenazadas_global_cr": 0,
      "registros_amenazadas_global_en": 0,
      "registros_amenazadas_global_vu": 0,
      "registros_amenazadas_global_nt": 1,
      "registros_amenazadas_global_lc": 0,
      "registros_amenazadas_global_dd": 0
    }
  ],
  "tematica": [
    {
      "slug_tematica": "amenazadas-global",
      "label": "Número de especies amenaza global",
      "count": 2246,
      "slug": "amenazadas-global",
      "title": "Lista especies: amenazadas-global",
      "chart": "static/charts/tolima/amenazadas-global.html"
    },
    {
      "slug_tematica": "amenazadas-global-cr",
      "label": "Especies CR categoría global",
      "count": 12,
      "slug": "amenazadas-global-cr",
      "title": "Lista especies: amenazadas-global-cr",
      "chart": "static/charts/tolima/amenazadas-global-cr.html"
    },
    {
      "slug_tematica": "amenazadas-global-dd",
      "label": "Especies DD categoría global",
      "count": 39,
      "slug": "amenazadas-global-dd",
      "title": "Lista especies: amenazadas-global-dd",
      "chart": "static/charts/tolima/amenazadas-global-dd.html"
    },
    {
      "slug_tematica": "amenazadas-global-en",
      "label": "Especies EN categoría global",
      "count": 44,
      "slug": "amenazadas-global-en",
      "title": "Lista especies: amenazadas-global-en",
      "chart": "static/charts/tolima/amenazadas-global-en.html"
    },
    {
      "slug_tematica": "amenazadas-global-ew",
      "label": "Especies EW categoría global",
      "count": 2,
      "slug": "amenazadas-global-ew",
      "title": "Lista especies: amenazadas-global-ew",
      "chart": "static/charts/tolima/amenazadas-global-ew.html"
    },
    {
      "slug_tematica": "amenazadas-global-ex",
      "label": "Especies EX categoría global",
      "count": 1,
      "slug": "amenazadas-global-ex",
      "title": "Lista especies: amenazadas-global-ex",
      "chart": "static/charts/tolima/amenazadas-global-ex.html"
    },
    {
      "slug_tematica": "amenazadas-global-lc",
      "label": "Especies LC categoría global",
      "count": 1995,
      "slug": "amenazadas-global-lc",
      "title": "Lista especies: amenazadas-global-lc",
      "chart": "static/charts/tolima/amenazadas-global-lc.html"
    },
    {
      "slug_tematica": "amenazadas-global-lr-lc",
      "label": "Especies LR/LC categoría global",
      "count": 3,
      "slug": "amenazadas-global-lr-lc",
      "title": "Lista especies: amenazadas-global-lr-lc",
      "chart": "static/charts/tolima/amenazadas-global-lr-lc.html"
    },
    {
      "slug_tematica": "amenazadas-global-lr-nt",
      "label": "Especies LR/NT categoría global",
      "count": 3,
      "slug": "amenazadas-global-lr-nt",
      "title": "Lista especies: amenazadas-global-lr-nt",
      "chart": "static/charts/tolima/amenazadas-global-lr-nt.html"
    },
    {
      "slug_tematica": "amenazadas-global-nt",
      "label": "Especies NT categoría global",
      "count": 58,
      "slug": "amenazadas-global-nt",
      "title": "Lista especies: amenazadas-global-nt",
      "chart": "static/charts/tolima/amenazadas-global-nt.html"
    },
    {
      "slug_tematica": "amenazadas-global-vu",
      "label": "Especies VU categoría global",
      "count": 89,
      "slug": "amenazadas-global-vu",
      "title": "Lista especies: amenazadas-global-vu",
      "chart": "static/charts/tolima/amenazadas-global-vu.html"
    },
    {
      "slug_tematica": "amenazadas-nacional",
      "label": "Número de especies amenaza nacional",
      "count": 128,
      "slug": "amenazadas-nacional",
      "title": "Lista especies: amenazadas-nacional",
      "chart": "static/charts/tolima/amenazadas-nacional.html"
    },
    {
      "slug_tematica": "amenazadas-nacional-cr",
      "label": "Especies CR categoría nacional",
      "count": 19,
      "slug": "amenazadas-nacional-cr",
      "title": "Lista especies: amenazadas-nacional-cr",
      "chart": "static/charts/tolima/amenazadas-nacional-cr.html"
    },
    {
      "slug_tematica": "amenazadas-nacional-en",
      "label": "Especies EN categoría nacional",
      "count": 31,
      "slug": "amenazadas-nacional-en",
      "title": "Lista especies: amenazadas-nacional-en",
      "chart": "static/charts/tolima/amenazadas-nacional-en.html"
    },
    {
      "slug_tematica": "amenazadas-nacional-vu",
      "label": "Especies VU categoría nacional",
      "count": 78,
      "slug": "amenazadas-nacional-vu",
      "title": "Lista especies: amenazadas-nacional-vu",
      "chart": "static/charts/tolima/amenazadas-nacional-vu.html"
    },
    {
      "slug_tematica": "cites",
      "label": "Número de especies CITES",
      "count": 322,
      "slug": "cites",
      "title": "Lista especies: cites",
      "chart": "static/charts/tolima/cites.html"
    },
    {
      "slug_tematica": "cites-i",
      "label": "Especies I CITES",
      "count": 15,
      "slug": "cites-i",
      "title": "Lista especies: cites-i",
      "chart": "static/charts/tolima/cites-i.html"
    },
    {
      "slug_tematica": "cites-i-ii",
      "label": "Especies I-II CITES",
      "count": 1,
      "slug": "cites-i-ii",
      "title": "Lista especies: cites-i-ii",
      "chart": "static/charts/tolima/cites-i-ii.html"
    },
    {
      "slug_tematica": "cites-ii",
      "label": "Especies II CITES",
      "count": 293,
      "slug": "cites-ii",
      "title": "Lista especies: cites-ii",
      "chart": "static/charts/tolima/cites-ii.html"
    },
    {
      "slug_tematica": "cites-iii",
      "label": "Especies III CITES",
      "count": 13,
      "slug": "cites-iii",
      "title": "Lista especies: cites-iii",
      "chart": "static/charts/tolima/cites-iii.html"
    },
    {
      "slug_tematica": "endemicas",
      "label": "Número especies éndemicas",
      "count": 612,
      "slug": "endemicas",
      "title": "Lista especies: endemicas",
      "chart": "static/charts/tolima/endemicas.html"
    },
    {
      "slug_tematica": "exotica-riesgo-invasion",
      "label": "Número especies exoticas con potencial de invasión",
      "count": 29,
      "slug": "exotica-riesgo-invasion",
      "title": "Lista especies: exotica-riesgo-invasion",
      "chart": "static/charts/tolima/exotica-riesgo-invasion.html"
    },
    {
      "slug_tematica": "exoticas",
      "label": "Número especies exoticas",
      "count": 152,
      "slug": "exoticas",
      "title": "Lista especies: exoticas",
      "chart": "static/charts/tolima/exoticas.html"
    },
    {
      "slug_tematica": "invasoras",
      "label": "Número especies invasoras",
      "count": 6,
      "slug": "invasoras",
      "title": "Lista especies: invasoras",
      "chart": "static/charts/tolima/invasoras.html"
    },
    {
      "slug_tematica": "migratorias",
      "label": "Número especies migratorias",
      "count": 89,
      "slug": "migratorias",
      "title": "Lista especies: migratorias",
      "chart": "static/charts/tolima/migratorias.html"
    }
  ],
  "territorio": {
    "municipios": {
      "charts": [
        {
          "title": "Especies por municipio",
          "path": "static/charts/tolima/region_municipios_1.html"
        },
        {
          "title": "Observaciones por municipio",
          "path": "static/charts/tolima/region_municipios_2.html"
        }
      ]
    },
    "reserva-forestal-la-planada": [
      {
        "title": "Próximamente tendrás acceso a la información de la reserva",
        "path": {}
      }
    ],
    "resguardo-indigena-pialapi-pueblo-viejo": [
      {
        "title": "Próximamente tendrás acceso a la información del resguardo",
        "path": {}
      }
    ]
  }
}
